Swachh-0.0.4.data/purelib/Swachh/PC_Cleaner.py
Swachh-0.0.4.data/purelib/Swachh/Swachh.py
Swachh-0.0.4.data/purelib/Swachh/__init__.py
Swachh-0.0.4.dist-info/LICENSE
Swachh-0.0.4.dist-info/METADATA
Swachh-0.0.4.dist-info/WHEEL
Swachh-0.0.4.dist-info/entry_points.txt
Swachh-0.0.4.dist-info/top_level.txt
Swachh-0.0.4.dist-info/RECORD
